<?xml version="1.0" encoding="UTF-8"?>
<!--
  JeroenVermeulen_BlockCache

  DISCLAIMER

  Do not edit or add to this file if you wish to upgrade this Module to
  newer versions in the future.

  @category     JeroenVermeulen
  @package      JeroenVermeulen_BlockCache
  @copyright    Copyright (c) 2015 Jeroen Vermeulen (http://www.jeroenvermeulen.eu)
-->
<!--suppress XmlUnboundNsPrefix -->
<config>
    <sections>
        <jeroenvermeulen_blockcache translate="label" module="jeroenvermeulen_blockcache">
            <label>JeroenVermeulen BlockCache</label>
            <tab>advanced</tab>
            <sort_order>10</sort_order>
            <show_in_default>1</show_in_default>
            <show_in_website>1</show_in_website>
            <show_in_store>1</show_in_store>
            <groups>
                <general translate="label" module="jeroenvermeulen_blockcache">
                    <label>General</label>
                    <sort_order>100</sort_order>
                    <show_in_default>1</show_in_default>
                    <show_in_website>1</show_in_website>
                    <show_in_store>1</show_in_store>
                    <frontend_type>text</frontend_type>
                    <frontend_model>jeroenvermeulen_blockcache/adminhtml_system_config_form_fieldset_first</frontend_model>
                    <fields>
                        <enable_formkey_fix translate="label comment">
                            <label>Enable FormKey Fix</label>
                            <frontend_type>select</frontend_type>
                            <source_model>adminhtml/system_config_source_yesno</source_model>
                            <sort_order>10</sort_order>
                            <show_in_default>1</show_in_default>
                            <show_in_website>1</show_in_website>
                            <show_in_store>1</show_in_store>
                        </enable_formkey_fix>
                        <log_miss translate="label comment">
                            <label>Log Cache Misses</label>
                            <comment>Logfile: var/log/cache_miss.log</comment>
                            <frontend_type>select</frontend_type>
                            <source_model>adminhtml/system_config_source_enabledisable</source_model>
                            <sort_order>20</sort_order>
                            <show_in_default>1</show_in_default>
                            <show_in_website>1</show_in_website>
                            <show_in_store>1</show_in_store>
                        </log_miss>
                    </fields>
                </general>
                <category_page translate="label" module="jeroenvermeulen_blockcache">
                    <label>Product List / Category Page</label>
                    <sort_order>200</sort_order>
                    <show_in_default>1</show_in_default>
                    <show_in_website>1</show_in_website>
                    <show_in_store>1</show_in_store>
                    <fields>
                        <enable_cache translate="label comment">
                            <label>Enable Caching</label>
                            <frontend_type>select</frontend_type>
                            <source_model>adminhtml/system_config_source_yesno</source_model>
                            <sort_order>10</sort_order>
                            <show_in_default>1</show_in_default>
                            <show_in_website>1</show_in_website>
                            <show_in_store>1</show_in_store>
                        </enable_cache>
                        <cache_when_url_param translate="label comment">
                            <label>Cache when URL parameters set</label>
                            <frontend_type>select</frontend_type>
                            <source_model>adminhtml/system_config_source_yesno</source_model>
                            <sort_order>15</sort_order>
                            <show_in_default>1</show_in_default>
                            <show_in_website>1</show_in_website>
                            <show_in_store>1</show_in_store>
                            <depends>
                                <enable_cache>1</enable_cache>
                            </depends>
                        </cache_when_url_param>
                        <lifetime translate="label">
                            <label>Life Time (Seconds)</label>
                            <frontend_type>text</frontend_type>
                            <sort_order>20</sort_order>
                            <validate>validate-greater-than-zero</validate>
                            <show_in_default>1</show_in_default>
                            <show_in_website>1</show_in_website>
                            <show_in_store>1</show_in_store>
                            <depends>
                                <enable_cache>1</enable_cache>
                            </depends>
                        </lifetime>
                        <enable_messages_fix translate="label comment">
                            <label>Enable Messages Fix</label>
                            <frontend_type>select</frontend_type>
                            <source_model>adminhtml/system_config_source_yesno</source_model>
                            <sort_order>30</sort_order>
                            <show_in_default>1</show_in_default>
                            <show_in_website>1</show_in_website>
                            <show_in_store>1</show_in_store>
                            <depends>
                                <enable_cache>1</enable_cache>
                            </depends>
                        </enable_messages_fix>
                    </fields>
                </category_page>
                <product_detail translate="label" module="jeroenvermeulen_blockcache">
                    <label>Product Detail Page</label>
                    <sort_order>300</sort_order>
                    <show_in_default>1</show_in_default>
                    <show_in_website>1</show_in_website>
                    <show_in_store>1</show_in_store>
                    <fields>
                        <enable_cache translate="label comment">
                            <label>Enable Caching</label>
                            <frontend_type>select</frontend_type>
                            <sort_order>10</sort_order>
                            <show_in_default>1</show_in_default>
                            <show_in_website>1</show_in_website>
                            <show_in_store>1</show_in_store>
                            <source_model>adminhtml/system_config_source_yesno</source_model>
                        </enable_cache>
                        <lifetime translate="label">
                            <label>Life Time (Seconds)</label>
                            <frontend_type>text</frontend_type>
                            <sort_order>20</sort_order>
                            <validate>validate-greater-than-zero</validate>
                            <show_in_default>1</show_in_default>
                            <show_in_website>1</show_in_website>
                            <show_in_store>1</show_in_store>
                            <depends>
                                <enable_cache>1</enable_cache>
                            </depends>
                        </lifetime>
                        <enable_messages_fix translate="label comment">
                            <label>Enable Messages Fix</label>
                            <frontend_type>select</frontend_type>
                            <source_model>adminhtml/system_config_source_yesno</source_model>
                            <sort_order>30</sort_order>
                            <show_in_default>1</show_in_default>
                            <show_in_website>1</show_in_website>
                            <show_in_store>1</show_in_store>
                            <depends>
                                <enable_cache>1</enable_cache>
                            </depends>
                        </enable_messages_fix>
                    </fields>
                </product_detail>
                <cms_page translate="label" module="jeroenvermeulen_blockcache">
                    <label>CMS Pages</label>
                    <sort_order>400</sort_order>
                    <show_in_default>1</show_in_default>
                    <show_in_website>1</show_in_website>
                    <show_in_store>1</show_in_store>
                    <fields>
                        <enable_cache translate="label comment">
                            <label>Enable Caching</label>
                            <frontend_type>select</frontend_type>
                            <source_model>adminhtml/system_config_source_yesno</source_model>
                            <sort_order>10</sort_order>
                            <show_in_default>1</show_in_default>
                            <show_in_website>1</show_in_website>
                            <show_in_store>1</show_in_store>
                        </enable_cache>
                        <lifetime translate="label">
                            <label>Life Time (Seconds)</label>
                            <frontend_type>text</frontend_type>
                            <sort_order>20</sort_order>
                            <validate>validate-greater-than-zero</validate>
                            <show_in_default>1</show_in_default>
                            <show_in_website>1</show_in_website>
                            <show_in_store>1</show_in_store>
                            <depends>
                                <enable_cache>1</enable_cache>
                            </depends>
                        </lifetime>
                    </fields>
                </cms_page>
                <layered_navigation translate="label" module="jeroenvermeulen_blockcache">
                    <label>Layered Navigation Block</label>
                    <sort_order>500</sort_order>
                    <show_in_default>1</show_in_default>
                    <show_in_website>1</show_in_website>
                    <show_in_store>1</show_in_store>
                    <fields>
                        <enable_cache translate="label comment">
                            <label>Enable Caching</label>
                            <frontend_type>select</frontend_type>
                            <source_model>adminhtml/system_config_source_yesno</source_model>
                            <sort_order>10</sort_order>
                            <show_in_default>1</show_in_default>
                            <show_in_website>1</show_in_website>
                            <show_in_store>1</show_in_store>
                        </enable_cache>
                        <lifetime translate="label">
                            <label>Life Time (Seconds)</label>
                            <frontend_type>text</frontend_type>
                            <sort_order>20</sort_order>
                            <validate>validate-greater-than-zero</validate>
                            <show_in_default>1</show_in_default>
                            <show_in_website>1</show_in_website>
                            <show_in_store>1</show_in_store>
                            <depends>
                                <enable_cache>1</enable_cache>
                            </depends>
                        </lifetime>
                    </fields>
                </layered_navigation>
                <cms_block translate="label" module="jeroenvermeulen_blockcache">
                    <label>CMS Static Blocks &amp; Widgets</label>
                    <sort_order>600</sort_order>
                    <show_in_default>1</show_in_default>
                    <show_in_website>1</show_in_website>
                    <show_in_store>1</show_in_store>
                    <fields>
                        <enable_cache translate="label comment">
                            <label>Enable Caching</label>
                            <frontend_type>select</frontend_type>
                            <source_model>adminhtml/system_config_source_yesno</source_model>
                            <sort_order>10</sort_order>
                            <show_in_default>1</show_in_default>
                            <show_in_website>1</show_in_website>
                            <show_in_store>1</show_in_store>
                        </enable_cache>
                        <lifetime translate="label">
                            <label>Life Time (Seconds)</label>
                            <frontend_type>text</frontend_type>
                            <sort_order>20</sort_order>
                            <validate>validate-greater-than-zero</validate>
                            <show_in_default>1</show_in_default>
                            <show_in_website>1</show_in_website>
                            <show_in_store>1</show_in_store>
                            <depends>
                                <enable_cache>1</enable_cache>
                            </depends>
                        </lifetime>
                    </fields>
                </cms_block>
                <flushes translate="label comment" module="jeroenvermeulen_blockcache">
                    <label>Cache Flushes</label>
                    <comment>These settings do not affect: <em>System &gt; Cache Management</em></comment>
                    <sort_order>1000</sort_order>
                    <show_in_default>1</show_in_default>
                    <show_in_website>1</show_in_website>
                    <show_in_store>1</show_in_store>
                    <fields>
                        <_log translate="label comment">
                            <label>Log Cache Flushes</label>
                            <comment>Logfile: var/log/cache_flush.log</comment>
                            <frontend_type>select</frontend_type>
                            <source_model>adminhtml/system_config_source_enabledisable</source_model>
                            <sort_order>10</sort_order>
                            <show_in_default>1</show_in_default>
                            <show_in_website>1</show_in_website>
                            <show_in_store>1</show_in_store>
                        </_log>
                        <catalog_category translate="label">
                            <label>On Category change</label>
                            <frontend_type>select</frontend_type>
                            <source_model>jeroenvermeulen_blockcache/system_config_source_cacheflushes</source_model>
                            <sort_order>100</sort_order>
                            <show_in_default>1</show_in_default>
                            <show_in_website>1</show_in_website>
                            <show_in_store>1</show_in_store>
                        </catalog_category>
                        <catalog_product translate="label">
                            <label>On Product change</label>
                            <frontend_type>select</frontend_type>
                            <source_model>jeroenvermeulen_blockcache/system_config_source_cacheflushes</source_model>
                            <sort_order>110</sort_order>
                            <show_in_default>1</show_in_default>
                            <show_in_website>1</show_in_website>
                            <show_in_store>1</show_in_store>
                        </catalog_product>
                        <cms_page translate="label">
                            <label>On CMS Page change</label>
                            <frontend_type>select</frontend_type>
                            <source_model>jeroenvermeulen_blockcache/system_config_source_cacheflushes</source_model>
                            <sort_order>120</sort_order>
                            <show_in_default>1</show_in_default>
                            <show_in_website>1</show_in_website>
                            <show_in_store>1</show_in_store>
                        </cms_page>
                        <cms_block translate="label">
                            <label>On CMS Block change</label>
                            <frontend_type>select</frontend_type>
                            <source_model>jeroenvermeulen_blockcache/system_config_source_cacheflushes</source_model>
                            <sort_order>130</sort_order>
                            <show_in_default>1</show_in_default>
                            <show_in_website>1</show_in_website>
                            <show_in_store>1</show_in_store>
                        </cms_block>
                        <translate translate="label">
                            <label>On Translation change</label>
                            <frontend_type>select</frontend_type>
                            <source_model>jeroenvermeulen_blockcache/system_config_source_cacheflushes</source_model>
                            <sort_order>140</sort_order>
                            <show_in_default>1</show_in_default>
                            <show_in_website>1</show_in_website>
                            <show_in_store>1</show_in_store>
                        </translate>
                        <store translate="label">
                            <label>On Store setting change</label>
                            <frontend_type>select</frontend_type>
                            <source_model>jeroenvermeulen_blockcache/system_config_source_cacheflushes</source_model>
                            <sort_order>150</sort_order>
                            <show_in_default>1</show_in_default>
                            <show_in_website>1</show_in_website>
                            <show_in_store>1</show_in_store>
                        </store>
                        <website translate="label">
                            <label>On Website settings change</label>
                            <frontend_type>select</frontend_type>
                            <source_model>jeroenvermeulen_blockcache/system_config_source_cacheflushes</source_model>
                            <sort_order>160</sort_order>
                            <show_in_default>1</show_in_default>
                            <show_in_website>1</show_in_website>
                            <show_in_store>1</show_in_store>
                        </website>
                        <block_html translate="label">
                            <label>Flush BLOCK_HTML</label>
                            <frontend_type>select</frontend_type>
                            <source_model>jeroenvermeulen_blockcache/system_config_source_cacheflushes</source_model>
                            <sort_order>170</sort_order>
                            <show_in_default>1</show_in_default>
                            <show_in_website>1</show_in_website>
                            <show_in_store>1</show_in_store>
                        </block_html>
                        <mage translate="label">
                            <label>Entire Magento Cache</label>
                            <frontend_type>select</frontend_type>
                            <source_model>jeroenvermeulen_blockcache/system_config_source_cacheflushes</source_model>
                            <sort_order>180</sort_order>
                            <show_in_default>1</show_in_default>
                            <show_in_website>1</show_in_website>
                            <show_in_store>1</show_in_store>
                        </mage>
                        <_without_tags translate="label">
                            <label>Wipe Cache Storage</label>
                            <frontend_type>select</frontend_type>
                            <source_model>jeroenvermeulen_blockcache/system_config_source_cacheflushes</source_model>
                            <sort_order>190</sort_order>
                            <show_in_default>1</show_in_default>
                            <show_in_website>1</show_in_website>
                            <show_in_store>1</show_in_store>
                        </_without_tags>
                    </fields>
                </flushes>
                <cache_warmer translate="label" module="jeroenvermeulen_blockcache">
                    <label>Cache Warmer</label>
                    <sort_order>700</sort_order>
                    <show_in_default>1</show_in_default>
                    <show_in_website>1</show_in_website>
                    <show_in_store>1</show_in_store>
                    <fields>
                        <user_agent translate="label comment">
                            <label>Cache Warmer UserAgent</label>
                            <comment>If the UserAgent of a visitor contains this text, it is considered to be a cache warmer request.</comment>
                            <frontend_type>text</frontend_type>
                            <sort_order>10</sort_order>
                            <show_in_default>1</show_in_default>
                            <show_in_website>1</show_in_website>
                            <show_in_store>1</show_in_store>
                        </user_agent>
                        <refresh_on_visit translate="label comment">
                            <label>On Cache Warmer Visit</label>
                            <frontend_type>select</frontend_type>
                            <source_model>jeroenvermeulen_blockcache/system_config_source_cachewarmervisit</source_model>
                            <sort_order>20</sort_order>
                            <show_in_default>1</show_in_default>
                            <show_in_website>1</show_in_website>
                            <show_in_store>1</show_in_store>
                        </refresh_on_visit>
                    </fields>
                </cache_warmer>
            </groups>
        </jeroenvermeulen_blockcache>
    </sections>
</config>